raga/Project.py
raga/__init__.py
raga/_tests.py
raga/constants.py
raga/dataset.py
raga/dataset_creds.py
raga/exception.py
raga/file_uploader.py
raga/filters.py
raga/inference.py
raga/lightmetrics.py
raga/model.py
raga/model_executor_factory.py
raga/post_deployment_checks.py
raga/raga_schema.py
raga/test_session.py
raga/docs/conf.py
raga/docs/index.rst
raga/llm/__init__.py
raga/llm/exporter/__init__.py
raga/llm/exporter/constants.py
raga/llm/exporter/s3exporter.py
raga/llm/instrumentation/__init__.py
raga/llm/instrumentation/langchain/__init__.py
raga/llm/instrumentation/langchain/constants.py
raga/llm/instrumentation/langchain/langchain_instrumentator.py
raga/llm/instrumentation/openai/__init__.py
raga/llm/instrumentation/openai/openai_instrumentator.py
raga/llm/instrumentation/openai/s3exporter.py
raga/utils/__init__.py
raga/utils/dataset_util.py
raga/utils/file.py
raga/utils/http_client.py
raga/utils/raga_config_reader.py
raga/validators/dataset_creds_validations.py
raga/validators/dataset_validations.py
raga/validators/test_session_validation.py
raga_testing_platform-1.1.79.dist-info/licenses/LICENSE
raga_testing_platform-1.1.79.dist-info/METADATA
raga_testing_platform-1.1.79.dist-info/WHEEL
raga_testing_platform-1.1.79.dist-info/top_level.txt
raga_testing_platform-1.1.79.dist-info/RECORD
