Metadata-Version: 2.4
Name: raga-testing-platform
Version: 1.1.79
Summary: Short description or overview of the raga package.
Author-email: Raga AI <support@ragaai.com>
Maintainer-email: Raga AI <support@ragaai.com>
Project-URL: Homepage, https://github.com/whoosh-labs/testing-platform-python-client
Project-URL: Bug Tracker, https://github.com/whoosh-labs/testing-platform-python-client/issues
Keywords: testing-platform,raga-testing-platform,model-testing,AB_testing
Classifier: Programming Language :: Python :: 3
Classifier: Programming Language :: Python :: 3.9
Classifier: Programming Language :: Python :: 3.10
Classifier: Programming Language :: Python :: 3.11
Classifier: License :: OSI Approved :: MIT License
Classifier: Operating System :: OS Independent
Requires-Python: >=3.9
License-File: LICENSE
Requires-Dist: pandas==2.0.2
Requires-Dist: urllib3==1.26.7
Requires-Dist: requests==2.31.0
Requires-Dist: numpy==1.24.3
Requires-Dist: halo==0.0.31
Requires-Dist: boto3==1.28.52
Requires-Dist: docker==7.0.0
Requires-Dist: langchain==0.1.13
Requires-Dist: langchain-community==0.0.30
Requires-Dist: langchain-openai==0.1.1
Requires-Dist: openai==1.14.3
Requires-Dist: opentelemetry-api==1.23.0
Requires-Dist: openinference-instrumentation-langchain==0.1.14
Requires-Dist: openinference-instrumentation-openai==0.1.4
Requires-Dist: opentelemetry-sdk==1.23.0
Dynamic: license-file
